maze_email_service/__init__.py
maze_email_service/client.py
maze_email_service/config.py
maze_email_service/exceptions.py
maze_email_service/logger.py
maze_email_service/models.py
maze_email_service/result.py
maze_email_service/sender.py
maze_email_service/templates.py
maze_email_service-1.0.1.dist-info/licenses/LICENSE
maze_email_service-1.0.1.dist-info/METADATA
maze_email_service-1.0.1.dist-info/WHEEL
maze_email_service-1.0.1.dist-info/top_level.txt
maze_email_service-1.0.1.dist-info/RECORD
