Metadata-Version: 2.4
Name: maze-email-service
Version: 1.0.1
Summary: Reusable email service using Azure Communication Services
Author-email: Your Name <you@company.com>
License: MIT
Requires-Python: >=3.9
License-File: LICENSE
Requires-Dist: azure-communication-email>=1.0.1
Requires-Dist: pydantic>=2.0
Requires-Dist: pydantic-settings>=2.0
Requires-Dist: jinja2>=3.1
Requires-Dist: email-validator>=2.3.0
Requires-Dist: pydantic-settings>=1.12.0
Provides-Extra: dev
Requires-Dist: pytest; extra == "dev"
Requires-Dist: black; extra == "dev"
Requires-Dist: ruff; extra == "dev"
Dynamic: license-file
